pyweatherflowrest/__init__.py
pyweatherflowrest/api.py
pyweatherflowrest/const.py
pyweatherflowrest/data.py
pyweatherflowrest/exceptions.py
pyweatherflowrest/helpers.py
pyweatherflowrest-1.0.11.dist-info/LICENSE
pyweatherflowrest-1.0.11.dist-info/METADATA
pyweatherflowrest-1.0.11.dist-info/WHEEL
pyweatherflowrest-1.0.11.dist-info/top_level.txt
pyweatherflowrest-1.0.11.dist-info/RECORD
