Metadata-Version: 2.1
Name: pyweatherflowrest
Version: 1.0.11
Summary: Python Wrapper for WeatherFlow Rest API
Home-page: https://github.com/briis/pyweatherflowrest
Author: Bjarne Riis
Author-email: bjarne@briis.com
License: MIT
Keywords: Home Assistant,Python,WeatherFlow
Classifier: Development Status :: 5 - Production/Stable
Classifier: Intended Audience :: Developers
Classifier: Topic :: Software Development :: Build Tools
Classifier: License :: OSI Approved :: MIT License
Classifier: Programming Language :: Python :: 3.8
Classifier: Programming Language :: Python :: 3.9
Classifier: Programming Language :: Python :: 3.10
License-File: LICENSE
Requires-Dist: aiohttp
